torchlinops/__init__.py
torchlinops/config.py
torchlinops/alg/__init__.py
torchlinops/alg/pcg.py
torchlinops/alg/poly.py
torchlinops/alg/powermethod.py
torchlinops/functional/__init__.py
torchlinops/functional/_nufft.py
torchlinops/functional/_pad.py
torchlinops/functional/_index/index.py
torchlinops/functional/_index/tests/bench_indexing.py
torchlinops/functional/_index/tests/test_index.py
torchlinops/functional/_interp/.gitignore
torchlinops/functional/_interp/__init__.py
torchlinops/functional/_interp/_batch.py
torchlinops/functional/_interp/_circ_pad.py
torchlinops/functional/_interp/grid.py
torchlinops/functional/_interp/interp.py
torchlinops/functional/_interp/kernels.py
torchlinops/functional/_interp/ungrid.py
torchlinops/functional/_interp/tests/_valid_pts.py
torchlinops/functional/_interp/tests/bench_grid1d.py
torchlinops/functional/_interp/tests/bench_grid2d.py
torchlinops/functional/_interp/tests/bench_grid3d.py
torchlinops/functional/_interp/tests/bench_ungrid1d.py
torchlinops/functional/_interp/tests/bench_ungrid2d.py
torchlinops/functional/_interp/tests/bench_ungrid3d.py
torchlinops/functional/_interp/tests/conftest.py
torchlinops/functional/_interp/tests/test_circular_pad.py
torchlinops/functional/_interp/tests/test_edgecases.py
torchlinops/functional/_interp/tests/test_grid.py
torchlinops/functional/_interp/tests/test_interp_diff.py
torchlinops/functional/_interp/tests/test_ungrid.py
torchlinops/functional/_unfold/array_to_blocks.py
torchlinops/functional/_unfold/casting.py
torchlinops/functional/_unfold/fold.py
torchlinops/functional/_unfold/nblocks.py
torchlinops/functional/_unfold/unfold.py
torchlinops/functional/_unfold/tests/.gitignore
torchlinops/functional/_unfold/tests/README.md
torchlinops/functional/_unfold/tests/bench_fold1d.py
torchlinops/functional/_unfold/tests/bench_fold2d.py
torchlinops/functional/_unfold/tests/bench_fold3d.py
torchlinops/functional/_unfold/tests/bench_unfold1d.py
torch_named_linops-0.5.2.dist-info/METADATA
torch_named_linops-0.5.2.dist-info/WHEEL
torch_named_linops-0.5.2.dist-info/RECORD
