Metadata-Version: 2.4
Name: torch-named-linops
Version: 0.5.2
Summary: A flexible linear operator abstraction in pytorch.
Author-email: Mark Nishimura <nishimuramarky@gmail.com>
Classifier: Development Status :: 3 - Alpha
Classifier: Programming Language :: Python :: 3.10
Classifier: Programming Language :: Python :: 3.11
Classifier: Programming Language :: Python :: 3.12
Requires-Python: <3.13,>=3.10
Requires-Dist: einops>=0.8.0
Requires-Dist: jaxtyping>=0.2.36
Requires-Dist: scipy>=1.15.2
Requires-Dist: setuptools>=75.6.0
Requires-Dist: torch<2.3,>1.13; sys_platform == 'darwin' and platform_machine == 'x86_64'
Requires-Dist: torch>=2.5.1; sys_platform != 'darwin' or platform_machine != 'x86_64'
Requires-Dist: torchaudio<2.3,>1.13; sys_platform == 'darwin' and platform_machine == 'x86_64'
Requires-Dist: torchaudio>=2.5.1; sys_platform != 'darwin' or platform_machine != 'x86_64'
Requires-Dist: torchvision<0.22.1; sys_platform == 'darwin' and platform_machine == 'x86_64'
Requires-Dist: torchvision>=0.20.1; sys_platform != 'darwin' or platform_machine != 'x86_64'
Requires-Dist: tqdm>=4.67.1
Requires-Dist: triton>=3.0; sys_platform != 'darwin'
